SCRC/serial_crc.v
// Function    : CCITT Serial CRC
module serial_crc(
    clk,
    reset,
    enable,
    init,
    data_in,
    crc_out
);
    input clk;
    input reset;
    input enable;
    input init;
    input data_in;
    output [15:0]crc_out;

    reg [15:0] lfsr;
    assign crc_out = lfsr;

    always @(posedge clk, posedge reset) begin
        if(reset) lfsr <= 16'hFFFF;
        else if (enable) begin
            if(init) lfsr <= 16'hFFFF;
            else begin
                lfsr[0] <= data_in^lfsr[15];
                lfsr[1] <=lfsr[0];
                lfsr[2] <=lfsr[1];
                lfsr[3] <=lfsr[2];
                lfsr[4] <=lfsr[3];
                lfsr[5] <=lfsr[4]^lfsr[15];//data_in^lfsr[15];
                lfsr[6] <=lfsr[5];
                lfsr[7] <=lfsr[6];
                lfsr[8] <=lfsr[7];
                lfsr[9] <=lfsr[8];
                lfsr[10] <=lfsr[9];
                lfsr[11] <=lfsr[10];
                lfsr[12] <=lfsr[11]^lfsr[15];//data_in^lfsr[15];
                lfsr[13] <=lfsr[12];
                lfsr[14] <=lfsr[13];
                lfsr[15] <=lfsr[14];
            end
        end
    end
endmodule

SCRC/scrc_tb.v
`include "serial_crc.v"
module scrc_tb(
    
);
    reg clk;
    reg reset;
    reg enable;
    reg init;
    reg data_in;
    wire [15:0]crc_out;

serial_crc serial_crc(
    .clk(clk),
    .reset(reset),
    .enable(enable),
    .init(init),
    .data_in(data_in),
    .crc_out(crc_out)
);
parameter CLOCKPERIOD = 10;
always #(CLOCKPERIOD/2) clk = !clk;
reg [23:0]data;
integer i;
initial begin
    $dumpfile("scrc.vcd");
    $dumpvars;
    clk = 0;
    reset = 0;
    enable = 0;
    init = 0;
    #10 reset = 1;
    #10 reset = 0;
    init = 1;
    #10 init = 0;
    
    data = 24'h000080;
    for (i=0; i<25; i++) begin
        #10
            enable = 0;
        #10 data_in = data[i];
            enable = 1;     
    end
    enable=0;
    //gencrc(8'h01,data_in,enable);
    #2000 $finish;
end

task gencrc;
    input [7:0]data;
    output dout;
    output enable;
    reg d;
    integer i;
    for (i=0; i<8; i++) begin
        #10
            enable = 0;
        #10 dout = data[i];
            enable = 1;
        
    end
endtask
endmodule

SCRC/scrc.vcd
$date
	Mon Feb 17 17:32:35 2020
$end
$version
	Icarus Verilog
$end
$timescale
	1s
$end
$scope module scrc_tb $end
$var wire 16 ! crc_out [15:0] $end
$var reg 1 " clk $end
$var reg 24 # data [23:0] $end
$var reg 1 $ data_in $end
$var reg 1 % enable $end
$var reg 1 & init $end
$var reg 1 ' reset $end
$var integer 32 ( i [31:0] $end
$scope module serial_crc $end
$var wire 1 " clk $end
$var wire 16 ) crc_out [15:0] $end
$var wire 1 $ data_in $end
$var wire 1 % enable $end
$var wire 1 & init $end
$var wire 1 ' reset $end
$var reg 16 * lfsr [15:0] $end
$upscope $end
$scope task gencrc $end
$var reg 8 + data [7:0] $end
$var reg 1 , dout $end
$var reg 1 - enable $end
$var integer 32 . i [31:0] $end
$upscope $end
$upscope $end
$enddefinitions $end
#0
$dumpvars
bx .
x-
x,
bx +
bx *
bx )
bx (
0'
0&
0%
x$
bx #
0"
bx !
$end
#5
1"
#10
b1111111111111111 !
b1111111111111111 )
b1111111111111111 *
0"
1'
#15
1"
#20
0"
1&
0'
#25
1"
#30
0"
b0 (
b10000000 #
0&
#35
1"
#40
0"
#45
1"
#50
0"
b1 (
1%
0$
#55
b1110111111011111 !
b1110111111011111 )
b1110111111011111 *
1"
#60
0"
0%
#65
1"
#70
0"
b10 (
1%
#75
b1100111110011111 !
b1100111110011111 )
b1100111110011111 *
1"
#80
0"
0%
#85
1"
#90
0"
b11 (
1%
#95
b1000111100011111 !
b1000111100011111 )
b1000111100011111 *
1"
#100
0"
0%
#105
1"
#110
0"
b100 (
1%
#115
b111000011111 !
b111000011111 )
b111000011111 *
1"
#120
0"
0%
#125
1"
#130
0"
b101 (
1%
#135
b1110000111110 !
b1110000111110 )
b1110000111110 *
1"
#140
0"
0%
#145
1"
#150
0"
b110 (
1%
#155
b11100001111100 !
b11100001111100 )
b11100001111100 *
1"
#160
0"
0%
#165
1"
#170
0"
b111 (
1%
#175
b111000011111000 !
b111000011111000 )
b111000011111000 *
1"
#180
0"
0%
#185
1"
#190
0"
b1000 (
1%
1$
#195
b1110000111110001 !
b1110000111110001 )
b1110000111110001 *
1"
#200
0"
0%
#205
1"
#210
0"
b1001 (
1%
0$
#215
b1101001111000011 !
b1101001111000011 )
b1101001111000011 *
1"
#220
0"
0%
#225
1"
#230
0"
b1010 (
1%
#235
b1011011110100111 !
b1011011110100111 )
b1011011110100111 *
1"
#240
0"
0%
#245
1"
#250
0"
b1011 (
1%
#255
b111111101101111 !
b111111101101111 )
b111111101101111 *
1"
#260
0"
0%
#265
1"
#270
0"
b1100 (
1%
#275
b1111111011011110 !
b1111111011011110 )
b1111111011011110 *
1"
#280
0"
0%
#285
1"
#290
0"
b1101 (
1%
#295
b1110110110011101 !
b1110110110011101 )
b1110110110011101 *
1"
#300
0"
0%
#305
1"
#310
0"
b1110 (
1%
#315
b1100101100011011 !
b1100101100011011 )
b1100101100011011 *
1"
#320
0"
0%
#325
1"
#330
0"
b1111 (
1%
#335
b1000011000010111 !
b1000011000010111 )
b1000011000010111 *
1"
#340
0"
0%
#345
1"
#350
0"
b10000 (
1%
#355
b1110000001111 !
b1110000001111 )
b1110000001111 *
1"
#360
0"
0%
#365
1"
#370
0"
b10001 (
1%
#375
b11100000011110 !
b11100000011110 )
b11100000011110 *
1"
#380
0"
0%
#385
1"
#390
0"
b10010 (
1%
#395
b111000000111100 !
b111000000111100 )
b111000000111100 *
1"
#400
0"
0%
#405
1"
#410
0"
b10011 (
1%
#415
b1110000001111000 !
b1110000001111000 )
b1110000001111000 *
1"
#420
0"
0%
#425
1"
#430
0"
b10100 (
1%
#435
b1101000011010001 !
b1101000011010001 )
b1101000011010001 *
1"
#440
0"
0%
#445
1"
#450
0"
b10101 (
1%
#455
b1011000110000011 !
b1011000110000011 )
b1011000110000011 *
1"
#460
0"
0%
#465
1"
#470
0"
b10110 (
1%
#475
b111001100100111 !
b111001100100111 )
b111001100100111 *
1"
#480
0"
0%
#485
1"
#490
0"
b10111 (
1%
#495
b1110011001001110 !
b1110011001001110 )
b1110011001001110 *
1"
#500
0"
0%
#505
1"
#510
0"
b11000 (
1%
#515
b1101110010111101 !
b1101110010111101 )
b1101110010111101 *
1"
#520
0"
0%
#525
1"
#530
0"
b11001 (
0%
x$
