divider/streamlinedDivider.v
`timescale 1ns/1ns
module STREAMLINEDDIVIDER(
    clk,
    rst_n,
    divisor,
    dividend,
    start_sig,

    done_sig,
    Quotient,
    Reminder
);
// input ports---------------
    input   clk;
    input   rst_n;
    input   start_sig;
    input   [7:0]divisor;
    input   [7:0]dividend;
// output ports---------------
    output  done_sig;
    output  [7:0]Quotient;//商
    output  [7:0]Reminder;//余数
// internal variables------------
    reg     [3:0]i;//步骤i
    reg     [8:0]s;//s为除数的负数补码表示
    reg     [15:0]Temp;//计算空间
    wire     [15:0]Diff;//每次用于计算差的结果
    reg     isNeg;
    reg     isDone;

    assign Diff = Temp + {s,7'd0};//减法
    assign done_sig = isDone;
    assign Quotient = isNeg?(~Temp[7:0]+1):Temp[7:0];
    assign Reminder = Temp[15:8];
    // codes start here--------------
    always@(posedge clk or negedge rst_n)
    if(!rst_n)//reset neg
    begin
        i <= 0;
        s <= 9'd0;
        Temp <= 16'd0;
        //Diff <= 16'd0;
        isNeg <= 0;
        isDone <= 0;
    end
    else if (start_sig) begin
        case (i)
            0:begin//初始化
                Temp <= dividend[7]?{8'd0,~dividend+1'b1}:{8'd0,dividend};//高8位全0，低八位被除数正数
                s <= divisor[7]?{divisor[7],divisor}:{1'b1,~divisor+1'b1};//s存放除数的负数补码值
                isNeg <= divisor[7]^dividend[7];//输出的符号
                //Diff <= 16'd0;
                i <= i+1'b1;
            end
            1,2,3,4,5,6,7,8:begin
                //Diff <= Temp + {s,7'd0};//减法
                if(Diff[15])    Temp <= {Temp[14:0],1'b0};//减法小于0 
                else    Temp <= {Diff[14:0],1'b1};//减法结果大于0
                i <= i+1'b1;
            end
            9:begin
                isDone <= 1'b1;
                i <= i+1'b1;
            end
            10:begin
                isDone <= 1'b0;
                i <= 0;
            end
            default: begin
                i <= 0;
            end
        endcase
    end

    
endmodule

divider/divider_tb.v
`include "streamlineddivider.v"
`timescale 1ns/1ns
module divider_tb(
    
);
    reg clk;
    reg rst_n;
    reg [7:0]divisor;
    reg [7:0]dividend;
    reg start_sig;

    wire done_sig;
    wire [7:0]Quotient;
    wire [7:0]Reminder;

STREAMLINEDDIVIDER u1_divider(
    .clk(clk),
    .rst_n(rst_n),
    .divisor(divisor),
    .dividend(dividend),
    .start_sig(start_sig),

    .done_sig(done_sig),
    .Quotient(Quotient),
    .Reminder(Reminder)
);
    
    initial begin
        $dumpfile("divider.vcd");
        $dumpvars;
        clk = 0;
        rst_n = 0;
        divisor = 8'd10;
        dividend = 8'd243;
        start_sig = 0;
        #10 rst_n = 1;
        //start_sig = 1;
        #10
        cal_divider(8'd10,8'd243,divisor,dividend,start_sig);

        #200 $finish;
    end
    
    always#5 clk = !clk;
    always@(done_sig)
    if(done_sig)
        start_sig = 0;

    task cal_divider;
        input   [7:0] A;
        input   [7:0] B;
        output  [7:0]divisor;
        output  [7:0]dividend;
        output  start_sig;
        begin
            divisor = A;
            dividend = B;
            start_sig = 1'b1;
        end
    endtask
endmodule

divider/divider.vcd
$date
	Thu Feb 20 16:27:37 2020
$end
$version
	Icarus Verilog
$end
$timescale
	1ns
$end
$scope module divider_tb $end
$var wire 1 ! done_sig $end
$var wire 8 " Reminder [7:0] $end
$var wire 8 # Quotient [7:0] $end
$var reg 1 $ clk $end
$var reg 8 % dividend [7:0] $end
$var reg 8 & divisor [7:0] $end
$var reg 1 ' rst_n $end
$var reg 1 ( start_sig $end
$scope module u1_divider $end
$var wire 1 $ clk $end
$var wire 8 ) dividend [7:0] $end
$var wire 8 * divisor [7:0] $end
$var wire 1 ! done_sig $end
$var wire 1 ' rst_n $end
$var wire 1 ( start_sig $end
$var wire 8 + Reminder [7:0] $end
$var wire 8 , Quotient [7:0] $end
$var wire 16 - Diff [15:0] $end
$var reg 16 . Temp [15:0] $end
$var reg 4 / i [3:0] $end
$var reg 1 0 isDone $end
$var reg 1 1 isNeg $end
$var reg 9 2 s [8:0] $end
$upscope $end
$scope task cal_divider $end
$var reg 8 3 A [7:0] $end
$var reg 8 4 B [7:0] $end
$var reg 8 5 dividend [7:0] $end
$var reg 8 6 divisor [7:0] $end
$var reg 1 7 start_sig $end
$upscope $end
$upscope $end
$enddefinitions $end
#0
$dumpvars
x7
bx 6
bx 5
bx 4
bx 3
b0 2
01
00
b0 /
b0 .
b0 -
b0 ,
b0 +
b1010 *
b11110011 )
0(
0'
b1010 &
b11110011 %
0$
b0 #
b0 "
0!
$end
#5
1$
#10
0$
1'
#15
1$
#20
0$
1(
17
b11110011 5
b1010 6
b11110011 4
b1010 3
#25
b11110011 #
b11110011 ,
b1 /
11
b111110110 2
b1111101100001101 -
b1101 .
1$
#30
0$
#35
b11100110 #
b11100110 ,
b10 /
b1111101100011010 -
b11010 .
1$
#40
0$
#45
b11001100 #
b11001100 ,
b11 /
b1111101100110100 -
b110100 .
1$
#50
0$
#55
b10011000 #
b10011000 ,
b100 /
b1111101101101000 -
b1101000 .
1$
#60
0$
#65
b110000 #
b110000 ,
b101 /
b1111101111010000 -
b11010000 .
1$
#70
0$
#75
b1100000 #
b1100000 ,
b1 "
b1 +
b110 /
b1111110010100000 -
b110100000 .
1$
#80
0$
#85
b11000000 #
b11000000 ,
b11 "
b11 +
b111 /
b1111111001000000 -
b1101000000 .
1$
#90
0$
#95
b10000000 #
b10000000 ,
b110 "
b110 +
b1000 /
b110000000 -
b11010000000 .
1$
#100
0$
#105
b11111111 #
b11111111 ,
b11 "
b11 +
b1001 /
b1111111000000001 -
b1100000001 .
1$
#110
0$
#115
0(
b1010 /
1!
10
1$
