float/adder.v
module adder(
    clk,
    rst_n,
    Start_Sig,
    A,
    B,
    Result,
    Done_Sig
);
    input   clk;
    input   rst_n;
    input   Start_Sig;
    input   [31:0]A;
    input   [31:0]B;

    output  [31:0]Result;
    output  [3:0]Done_Sig;//isOver,isUnder,isZero,isDone

    reg     [3:0]  i;
    reg     [56:0]rA,rB;//[56]Sign,[55:48]Exponent,[47:46]Hidden Bit,[45:23]Mantissa,[22:0]M'Backup
    reg     [48:0]Temp;//[48]M'Sign,[47:46]Hidden Bit,[45:23]M,[22:0]M'Backup
    reg     [48:0]TempA,TempB;
    reg     [31:0]rResult;
    wire     [9:0]rExp;//[9:8]Overflow or underflow check,[7;0]usual exp
    reg     [9:0]rExpValue;
    reg     [7:0]rExpDiff;//different between A.EXP and B.EXP
    reg     isSign;
    reg     isOver;
    reg     isUnder;
    reg     isZero;
    reg     isDone;

    assign rExp = A[30:23]-B[30:23];//价码差值
    always@(posedge clk or negedge rst_n)
    if(!rst_n)
    begin
        i <= 0;
        rA <= 0;
        rB <= 0;
        Temp <= 0;
        TempA <= 0;
        TempB <= 0;
        rResult <= 0;
        //rExp <= 0;
        rExpDiff <= 0;
        isSign <= 0;
        isOver <= 0;
        isUnder <= 0;
        isZero <= 0;
        isDone <= 0;
        rExpValue <= 0;
    end
    else if(Start_Sig)//使能控制，后面可以改为触发控制
    begin
        case(i)
            0:begin//initial A,B and other reg
                rA <= {A[31],A[30:23],2'b01,A[22:0],23'd0};
                rB <= {B[31],B[30:23],2'b01,B[22:0],23'd0};

                isOver <= 1'b0;
                isUnder <= 1'b0;
                isZero <= 1'b0;
                i <= i+1'b1;
            end
            1://价码对齐,可以和第一步合并
            begin
                if(rExp[8] == 1)//A<B
                    rExpDiff <= ~rExp[7:0] + 1'b1;//价码差值
                else 
                    rExpDiff <= rExp[7:0];
                i <= i+1; 
            end
            2://,可以和上一步合并
            begin
                if(rExp[8]==1)//A<B
                begin   
                    rA[47:0] <= rA[47:0]>>(rExpDiff);
                    rA[55:48] <= rB[55:48];
                end else begin
                    rB[47:0] <= rB[47:0]>>(rExpDiff);
                    rB[55:48] <= rA[55:48];
                end
                i <= i+1'b1;
            end
            3://补码转换
            begin   
                TempA <= rA[56]?{rA[56],(~rA[47:0]+1'b1)}:{rA[56],rA[47:0]};
                TempB <= rB[56]?{rB[56],(~rB[47:0]+1'b1)}:{rB[56],rB[47:0]};
                i <= i+1'b1;
            end
            4://加减运算
            begin
                Temp <= TempA + TempB;
                i <= i+1'b1;
            end
            5://补码转换为原码
            begin
                isSign <= Temp[48];
                if(Temp[48]== 1'b1)//结果<0
                    Temp <= ~Temp+1'b1;
                rExpValue <= {2'b00,rA[55:48]};//价码缓存
                i <= i+1'b1;
            end
            6://移位
            begin
                if(Temp[47:46]==2'b10||Temp[47:46]==2'b11)
                begin
                    Temp <= Temp>>1;//尾数
                    rExpValue <= rExpValue+1'b1;//指数
                end 
                else if (Temp[47:46] ==2'b00 && Temp[45] == 1'b1) begin
                    Temp <= Temp << 1;
                    rExpValue <= rExpValue-5'd1;
                end
                else if(Temp[47:46] ==2'b00 && Temp[44] == 1'b1)begin
                    Temp <= Temp << 2;
                    rExpValue <= rExpValue-5'd2;
                end
                else if(Temp[47:46] ==2'b00 && Temp[43] == 1'b1)begin
                    Temp <= Temp << 3;
                    rExpValue <= rExpValue-5'd3;
                end
                else if(Temp[47:46] ==2'b00 && Temp[42] == 1'b1)begin
                    Temp <= Temp << 4;
                    rExpValue <= rExpValue-5'd4;
                end
                else if(Temp[47:46] ==2'b00 && Temp[41] == 1'b1)begin
                    Temp <= Temp << 5;
                    rExpValue <= rExpValue-5'd5;
                end
                else if(Temp[47:46] ==2'b00 && Temp[40] == 1'b1)begin
                    Temp <= Temp << 6;
                    rExpValue <= rExpValue-5'd6;
                end
                else if(Temp[47:46] ==2'b00 && Temp[39] == 1'b1)begin
                    Temp <= Temp << 7;
                    rExpValue <= rExpValue-5'd7;
                end
                else if(Temp[47:46] ==2'b00 && Temp[38] == 1'b1)begin
                    Temp <= Temp << 8;
                    rExpValue <= rExpValue-5'd8;
                end
                else if(Temp[47:46] ==2'b00 && Temp[37] == 1'b1)begin
                    Temp <= Temp << 9;
                    rExpValue <= rExpValue-5'd9;
                end
                else if(Temp[47:46] ==2'b00 && Temp[36] == 1'b1)begin
                    Temp <= Temp << 10;
                    rExpValue <= rExpValue-5'd10;
                end
                else if(Temp[47:46] ==2'b00 && Temp[35] == 1'b1)begin
                    Temp <= Temp << 11;
                    rExpValue <= rExpValue-5'd11;
                end
                else if(Temp[47:46] ==2'b00 && Temp[34] == 1'b1)begin
                    Temp <= Temp << 12;
                    rExpValue <= rExpValue-5'd12;
                end
                else if(Temp[47:46] ==2'b00 && Temp[33] == 1'b1)begin
                    Temp <= Temp << 13;
                    rExpValue <= rExpValue-5'd13;
                end
                else if(Temp[47:46] ==2'b00 && Temp[32] == 1'b1)begin
                    Temp <= Temp << 14;
                    rExpValue <= rExpValue-5'd14;
                end
                else if(Temp[47:46] ==2'b00 && Temp[31] == 1'b1)begin
                    Temp <= Temp << 15;
                    rExpValue <= rExpValue-5'd15;
                end
                else if(Temp[47:46] ==2'b00 && Temp[30] == 1'b1)begin
                    Temp <= Temp << 16;
                    rExpValue <= rExpValue-5'd16;
                end
                else if(Temp[47:46] ==2'b00 && Temp[29] == 1'b1)begin
                    Temp <= Temp << 17;
                    rExpValue <= rExpValue-5'd17;
                end
                else if(Temp[47:46] ==2'b00 && Temp[28] == 1'b1)begin
                    Temp <= Temp << 18;
                    rExpValue <= rExpValue-5'd18;
                end
                else if(Temp[47:46] ==2'b00 && Temp[27] == 1'b1)begin
                    Temp <= Temp << 19;
                    rExpValue <= rExpValue-5'd19;
                end
                else if(Temp[47:46] ==2'b00 && Temp[26] == 1'b1)begin
                    Temp <= Temp << 20;
                    rExpValue <= rExpValue-5'd20;
                end
                else if(Temp[47:46] ==2'b00 && Temp[25] == 1'b1)begin
                    Temp <= Temp << 21;
                    rExpValue <= rExpValue-5'd21;
                end
                else if(Temp[47:46] ==2'b00 && Temp[24] == 1'b1)begin
                    Temp <= Temp << 22;
                    rExpValue <= rExpValue-5'd22;
                end
                else if(Temp[47:46] ==2'b00 && Temp[23] == 1'b1)begin
                    Temp <= Temp << 23;
                    rExpValue <= rExpValue-5'd23;
                end
                else if(Temp[47:46] ==2'b00 && Temp[22] == 1'b1)begin
                    Temp <= Temp << 24;
                    rExpValue <= rExpValue-5'd24;
                end
                else if(Temp[47:46] ==2'b00 && Temp[24] == 1'b1)begin
                    Temp <= Temp << 25;
                    rExpValue <= rExpValue-5'd25;
                end
                i <= i+1'b1;
            end
            7://溢出校验
            begin
                if(rExpValue[9:8] == 2'b01)//overflow
                begin
                    isOver <= 0;
                    rResult <= {1'b0,8'd127,23'd0};
                end
                else if(rExpValue[9:8] == 2'b11)//underflow
                begin
                    isUnder <= 0;
                    rResult <= {1'b0,8'd127,23'd0};
                end
                else if(Temp[46:23] == 24'd0)//zero
                begin
                    isZero <= 0;
                    rResult <= {1'b0,8'd127,23'd0};
                end
                else if(Temp[22]==1'b1)
                    rResult <= {isSign,rExpValue[7:0],Temp[45:23],1'b1};
                else    
                    rResult <= {isSign,rExpValue[7:0],Temp[45:23]};
                i <= i+1'b1;
            end
            8:
            begin
                isDone <= 1'b1;
                i <= i+1'b1;
            end
            9:
            begin
                isDone <= 1'b0;
                i <= i+1'b1;
            end

            default:i <= 0;

        endcase
    end
   
   assign Done_Sig = {isOver,isUnder,isZero,isDone};
   assign Result = rResult;

   
endmodule

float/adder_tb.v
`include "adder.v"
`timescale 1ps/1ps 
module float_add_module_simulation();
reg CLK;
reg RSTn;
reg Start_Sig; 
reg [31:0]A;
reg [31:0] B; 
wire [3:0] Done_Sig; 
wire [31:0] Result;
/*******************/ 
// wire [56:0]SQ_rA,SQ_rB;
// wire [48:0]SQ_Temp,SQ_TempA,SQ_TempB;
// wire [9:0]SQ_rExp; 
// wire [7:0]SQ_rExpDiff;
 /**********************************/ 
adder U1 ( 
    .clk(CLK ),
    .rst_n( RSTn), 
    .A(A),
    .B(B ),
    .Result(Result ), 
    .Start_Sig( Start_Sig), 
    .Done_Sig(Done_Sig) 
    // .SQ_rA(SQ_rA), 
    // .SQ_rB(SQ_rB)

// .SQ_Temp( SQ_Temp),
// .SQ_TempA(SQ_TempA), 
// .SQ_TempB(SQ_TempB), 
// .SQ_rExp( SQ_rExp ),
// .SQ_rExpDiff( SQ_rExpDiff) 
);
/***********************************/ 
initial begin 
    $dumpfile("adder.vcd");
    $dumpvars;
    RSTn= 0;CLK = 0;  #10 RSTn= 1; 
    //forever #5 CLK = ~CLK;
    #2000 $finish;

end 
always #5 CLK = !CLK;
/***********************************/ 
reg [3:0]i; 
always @ ( posedge CLK or negedge RSTn )
if(!RSTn) 
begin 
    A<= 32'd0; 
    B <= 32'd0; 
    Start_Sig<= 1'b0; 
    i <= 4'd0;
end 
else
case( i )
    0: //A=3.65, B= -7.4,A+B = ? 
    if(Done_Sig[0]) 
    begin 
        Start_Sig <= 1'b0; 
        i <= i + 1'b1; 
        $display("%b",Result); 
    end 
    else begin
        A<= 32'b0_10000000_11010011001100110011010; 
        B <= 32'b1_10000001_11011001100110011001101; 
        Start_Sig <= 1'b1; 
    end 
    1: //Exp undeflow check 
    if(Done_Sig[0]) begin 
        Start_Sig <= 1'b0; 
        i <= i + 1'b1; 
    end 
    else begin
        A<= 32'b0_00000000_01010000101101000101101; 
        B <= 32'b1_00000000_00010000101100001000111;
        Start_Sig <= 1'b1; 
    end
    2://A=1.9999997, B=-1.9999998,A+B=?
    if(Done_Sig[0] )begin 
        Start_Sig<= 1'b0; 
        i <= i + 1'b1; 
        $display("%b",Result); 
    end 
    else begin
        A<= 32'b0_01111111_11111111111111111111110;
        B <= 32'b1_01111111_11111111111111111111111; 
        Start_Sig <= 1'b1;
    end 
    3: //Exp Overflow 
    if(Done_Sig[0]) begin 
        Start_Sig <= 1'b0; 
        i <= i + 1'b1; end 
    else begin
        A<= 32'b0_11111111_11111111111111111111111; 
        B <= 32'b0_11111111_11111111111111111111111;
        Start_Sig <= 1'b1; 
    end

    4://A= -12.558, B= -7.309 ,A+B =? 
    if(Done_Sig[0] )begin 
        Start_Sig<= 1'b0; 
        i <= i + 1'b1; 
        $display("%b",Result);
    end 
    else begin
        A<= 32'b11000001010010001110110110010001; 
        B <= 32'b11000000111010011110001101010100; 
        Start_Sig <= 1'b1; end
    5://A= 111.7762, B= 302.4409 ,A+B =? 
    if(Done_Sig[0] )begin 
        Start_Sig<= 1'b0;
        i <= i + 1'b1; 
        $display("%b",Result); 
    end 
    else begin
        A<= 32'b01000010110111111000110101101010; 
        B <= 32'b01000011100101110011100001101111; 
        Start_Sig <= 1'b1; 
    end 
    6://A= 2112.2012, B= -2002.2012,A+B=? 
    if(Done_Sig[0] )begin 
        Start_Sig<= 1'b0; 
        i <= i + 1'b1; 
        $display("%b",Result); end 
    else begin
        A<= 32'b01000101000001000000001100111000; 
        B <= 32'b11000100111110100100011001110000; 
        Start_Sig <= 1'b1; end 
    7:
        i <= i;
    endcase
        
endmodule

float/adder.vcd
$date
	Fri Feb 28 11:24:03 2020
$end
$version
	Icarus Verilog
$end
$timescale
	1ps
$end
$scope module float_add_module_simulation $end
$var wire 32 ! Result [31:0] $end
$var wire 4 " Done_Sig [3:0] $end
$var reg 32 # A [31:0] $end
$var reg 32 $ B [31:0] $end
$var reg 1 % CLK $end
$var reg 1 & RSTn $end
$var reg 1 ' Start_Sig $end
$var reg 4 ( i [3:0] $end
$scope module U1 $end
$var wire 32 ) A [31:0] $end
$var wire 32 * B [31:0] $end
$var wire 32 + Result [31:0] $end
$var wire 1 ' Start_Sig $end
$var wire 1 % clk $end
$var wire 1 & rst_n $end
$var wire 10 , rExp [9:0] $end
$var wire 4 - Done_Sig [3:0] $end
$var reg 49 . Temp [48:0] $end
$var reg 49 / TempA [48:0] $end
$var reg 49 0 TempB [48:0] $end
$var reg 4 1 i [3:0] $end
$var reg 1 2 isDone $end
$var reg 1 3 isOver $end
$var reg 1 4 isSign $end
$var reg 1 5 isUnder $end
$var reg 1 6 isZero $end
$var reg 57 7 rA [56:0] $end
$var reg 57 8 rB [56:0] $end
$var reg 8 9 rExpDiff [7:0] $end
$var reg 10 : rExpValue [9:0] $end
$var reg 32 ; rResult [31:0] $end
$upscope $end
$upscope $end
$enddefinitions $end
#0
$dumpvars
b0 ;
b0 :
b0 9
b0 8
b0 7
06
05
04
03
02
b0 1
b0 0
b0 /
b0 .
b0 -
bx ,
b0 +
bx *
bx )
bx (
x'
0&
0%
bx $
bx #
b0 "
b0 !
$end
#5
b0 ,
b0 (
0'
b0 $
b0 *
b0 #
b0 )
1%
#10
0%
1&
#15
b1111111111 ,
1'
b11000000111011001100110011001101 $
b11000000111011001100110011001101 *
b1000000011010011001100110011010 #
b1000000011010011001100110011010 )
1%
#20
0%
#25
b1 1
b110000001011101100110011001100110100000000000000000000000 8
b10000000011101001100110011001101000000000000000000000000 7
1%
#30
0%
#35
b10 1
b1 9
1%
#40
0%
#45
b11 1
b10000001001110100110011001100110100000000000000000000000 7
1%
#50
0%
#55
b100 1
b1100010011001100110011001100000000000000000000000 0
b1110100110011001100110100000000000000000000000 /
1%
#60
0%
#65
b101 1
b1110001000000000000000000000000000000000000000000 .
1%
#70
0%
#75
b110 1
b10000001 :
b1111000000000000000000000000000000000000000000 .
14
1%
#80
0%
#85
b111 1
b10000000 :
b11110000000000000000000000000000000000000000000 .
1%
#90
0%
#95
b1000 1
b11000000011100000000000000000000 !
b11000000011100000000000000000000 +
b11000000011100000000000000000000 ;
1%
#100
0%
#105
b1001 1
b1 "
b1 -
12
1%
#110
0%
#115
b1010 1
b0 "
b0 -
02
b1 (
0'
1%
#120
0%
#125
b0 ,
1'
b10000000000010000101100001000111 $
b10000000000010000101100001000111 *
b1010000101101000101101 #
b1010000101101000101101 )
1%
#130
0%
#135
b0 1
1%
#140
0%
#145
b1 1
b100000000010001000010110000100011100000000000000000000000 8
b10101000010110100010110100000000000000000000000 7
1%
#150
0%
#155
b10 1
b0 9
1%
#160
0%
#165
b11 1
1%
#170
0%
#175
b100 1
b1101110111101001111011100100000000000000000000000 0
b10101000010110100010110100000000000000000000000 /
1%
#180
0%
#185
b101 1
b100000000000011110011000000000000000000000000 .
1%
#190
0%
#195
b110 1
b0 :
04
1%
#200
0%
#205
b111 1
b1111111110 :
b10000000000001111001100000000000000000000000000 .
1%
#210
0%
#215
b1000 1
b111111100000000000000000000000 !
b111111100000000000000000000000 +
b111111100000000000000000000000 ;
1%
#220
0%
#225
b1001 1
b1 "
b1 -
12
1%
#230
0%
#235
b1010 1
b0 "
b0 -
02
b10 (
0'
1%
#240
0%
#245
b0 ,
1'
b10111111111111111111111111111111 $
b10111111111111111111111111111111 *
b111111111111111111111111111110 #
b111111111111111111111111111110 )
1%
#250
0%
#255
b0 1
1%
#260
0%
#265
b1 1
b101111111011111111111111111111111100000000000000000000000 8
b1111111011111111111111111111111000000000000000000000000 7
1%
#270
0%
#275
b10 1
1%
#280
0%
#285
b11 1
1%
#290
0%
#295
b100 1
b1100000000000000000000000100000000000000000000000 0
b11111111111111111111111000000000000000000000000 /
1%
#300
0%
#305
b101 1
b1111111111111111111111111100000000000000000000000 .
1%
#310
0%
#315
b110 1
b1111111 :
b100000000000000000000000 .
14
1%
#320
0%
#325
b111 1
b1101000 :
b10000000000000000000000000000000000000000000000 .
1%
#330
0%
#335
b1000 1
b10110100000000000000000000000000 !
b10110100000000000000000000000000 +
b10110100000000000000000000000000 ;
1%
#340
0%
#345
b1001 1
b1 "
b1 -
12
1%
#350
0%
#355
b1010 1
b0 "
b0 -
02
b11 (
0'
1%
#360
0%
#365
b0 ,
1'
b1111111111111111111111111111111 $
b1111111111111111111111111111111 *
b1111111111111111111111111111111 #
b1111111111111111111111111111111 )
1%
#370
0%
#375
b0 1
1%
#380
0%
#385
b1 1
b11111111011111111111111111111111100000000000000000000000 8
b11111111011111111111111111111111100000000000000000000000 7
1%
#390
0%
#395
b10 1
1%
#400
0%
#405
b11 1
1%
#410
0%
#415
b100 1
b11111111111111111111111100000000000000000000000 0
b11111111111111111111111100000000000000000000000 /
1%
#420
0%
#425
b101 1
b111111111111111111111111000000000000000000000000 .
1%
#430
0%
#435
b110 1
b11111111 :
04
1%
#440
0%
#445
b111 1
b100000000 :
b11111111111111111111111100000000000000000000000 .
1%
#450
0%
#455
b1000 1
b111111100000000000000000000000 !
b111111100000000000000000000000 +
b111111100000000000000000000000 ;
1%
#460
0%
#465
b1001 1
b1 "
b1 -
12
1%
#470
0%
#475
b1010 1
b0 "
b0 -
02
b100 (
0'
1%
#480
0%
#485
b1 ,
1'
b11000000111010011110001101010100 $
b11000000111010011110001101010100 *
b11000001010010001110110110010001 #
b11000001010010001110110110010001 )
1%
#490
0%
#495
b0 1
1%
#500
0%
#505
b1 1
b110000001011101001111000110101010000000000000000000000000 8
b110000010011001000111011011001000100000000000000000000000 7
1%
#510
0%
#515
b10 1
b1 9
1%
#520
0%
#525
b11 1
b110000010001110100111100011010101000000000000000000000000 8
1%
#530
0%
#535
b100 1
b1110001011000011100101011000000000000000000000000 0
b1100110111000100100110111100000000000000000000000 /
1%
#540
0%
#545
b101 1
b1011000010001000001100010100000000000000000000000 .
1%
#550
0%
#555
b110 1
b10000010 :
b100111101110111110011101100000000000000000000000 .
14
1%
#560
0%
#565
b111 1
b10000011 :
b10011110111011111001110110000000000000000000000 .
1%
#570
0%
#575
b1000 1
b10000011001111011101111100111011 !
b10000011001111011101111100111011 +
b10000011001111011101111100111011 ;
1%
#580
0%
#585
b1001 1
b1 "
b1 -
12
1%
#590
0%
#595
b1010 1
b0 "
b0 -
02
b101 (
0'
1%
#600
0%
#605
b1111111110 ,
1'
b1000011100101110011100001101111 $
b1000011100101110011100001101111 *
b1000010110111111000110101101010 #
b1000010110111111000110101101010 )
1%
#610
0%
#615
b0 1
1%
#620
0%
#625
b1 1
b10000111010010111001110000110111100000000000000000000000 8
b10000101011011111100011010110101000000000000000000000000 7
1%
#630
0%
#635
b10 1
b10 9
1%
#640
0%
#645
b11 1
b10000111000110111111000110101101010000000000000000000000 7
1%
#650
0%
#655
b100 1
b10010111001110000110111100000000000000000000000 0
b110111111000110101101010000000000000000000000 /
1%
#660
0%
#665
b101 1
b11001111000110111100100110000000000000000000000 .
1%
#670
0%
#675
b110 1
b10000111 :
04
1%
#680
0%
#685
b111 1
1%
#690
0%
#695
b1000 1
b10000111100111100011011110010011 !
b10000111100111100011011110010011 +
b10000111100111100011011110010011 ;
1%
#700
0%
#705
b1001 1
b1 "
b1 -
12
1%
#710
0%
#715
b1010 1
b0 "
b0 -
02
b110 (
0'
1%
#720
0%
#725
b1 ,
1'
b11000100111110100100011001110000 $
b11000100111110100100011001110000 *
b1000101000001000000001100111000 #
b1000101000001000000001100111000 )
1%
#730
0%
#735
b0 1
1%
#740
0%
#745
b1 1
b110001001011111010010001100111000000000000000000000000000 8
b10001010010000100000000110011100000000000000000000000000 7
1%
#750
0%
#755
b10 1
b1 9
1%
#760
0%
#765
b11 1
b110001010001111101001000110011100000000000000000000000000 8
1%
#770
0%
#775
b100 1
b1110000010110111001100100000000000000000000000000 0
b10000100000000110011100000000000000000000000000 /
1%
#780
0%
#785
b101 1
b110111000000000000000000000000000000000000 .
1%
#790
0%
#795
b110 1
b10001010 :
1%
#800
0%
#805
b111 1
b10000101 :
b11011100000000000000000000000000000000000000000 .
1%
#810
0%
#815
b1000 1
b1000010110111000000000000000000 !
b1000010110111000000000000000000 +
b1000010110111000000000000000000 ;
1%
#820
0%
#825
b1001 1
b1 "
b1 -
12
1%
#830
0%
#835
b1010 1
b0 "
b0 -
02
b111 (
0'
1%
