float/multiplyer.v
module multiplyer(
    clk,
    rst_n,
    A,
    B,
    result,
    start_sig,
    done_sig
);
    input   clk;
    input   rst_n;
    input   [31:0]A;
    input   [31:0]B;
    input   start_sig;

    output  [31:0]result;
    output  [3:0]done_sig;

    reg     [32:0]rA;//{A[31:23],1'b1,A[22:0]}
    reg     [32:0]rB;//{B[31:23],1'b1,B[22:0]}

    reg     rSign;
    reg     [9:0]rExp;//[9:8]overflow or underflow [7:0]
    reg     [47:0]rM;
    reg     [31:0]rResult;
    reg     isOver;
    reg     isUnder;
    reg     isZero;
    reg     isDone;
    

    reg     [4:0]i;

    assign  done_sig = {isOver,isUnder,isZero,isDone};
    assign  result = rResult;
    always@(posedge clk or negedge rst_n)
    if(!rst_n)
    begin
        rA <= 0;//{A[31:23],1'b1,A[22:0]}
        rB <= 0;//{B[31:23],1'b1,B[22:0]}

        rSign <= 0;
        rExp <= 0;//[9:8]overflow or underflow [7:0]
        rM <= 0;
        rResult <= 0;
        isOver <= 0;
        isUnder <= 0;
        isZero <= 0;
        isDone <= 0;
    end
    else if(start_sig)
    begin
        case (i)
            0://初始化待处理数据
            begin
                rA <= {A[31:23],1'b1,A[22:0]};
                rB <= {B[31:23],1'b1,B[22:0]};

                rSign <= A[31]^B[31];
                rExp <= A[30:23]+B[30:23]-8'd127+1'b1;
                rM <= {1'b1,A[22:0]}*{1'b1,B[22:0]};

                i <= i + 1'b1;
            end
            1:
            begin
                if(rM[47] ==  1'b1) 
                    rM <= rM;
                else if(rM[46] ==  1'b1)
                begin
                    rM <= rM << 1;
                    rExp <= rExp -1'b1;
                end else if(rM[45]==1'b1)
                begin
                    rM <= rM << 2;
                    rExp <= rExp - 2'd2;
                end
                i <= i+1'b1;
            end
            2:
            begin
                if(rExp[9:8]==2'b01)
                begin
                    isOver <= 1'b1;
                    rResult <= {1'b0,8'd127,23'd0};
                end else if(rExp==2'b11)
                begin
                    isUnder <= 1'b1;
                    rResult <= {1'b0,8'd127,23'd0};
                end else if(rM[47:24]==24'd0)
                begin
                    isZero <= 1'b1;
                    rResult <= {1'b0,8'd127,23'd0};
                end else if(rM[23]== 1'b1)//四舍五入
                    rResult <= {rSign,rExp[7:0],rM[46:24]};//+1'b1};
                else
                    rResult <= {rSign,rExp[7:0],rM[46:24]};
                i <= i+1'b1;
            end
            3:
            begin
                isDone <= 1'b1;
                i <= i+1'b1;
            end
            4:
            begin
                isDone <= 1'b0;
                i <= 0;
            end
            default:i <= 0;
        endcase
    end
endmodule

float/multi_tb.v
`include "multiplyer.v"
`timescale 1ps/1ps
module multi_tb(
    
);

    reg clk;
    reg rst_n;
    reg [31:0]A;
    reg [31:0]B;
    wire [31:0]result;
    reg start_sig;
    wire [3:0]done_sig;

    multiplyer U1(
    .clk(clk),
    .rst_n(rst_n),
    .A(A),
    .B(B),
    .result(result),
    .start_sig(start_sig),
    .done_sig(done_sig)
);

initial begin
    $dumpfile("multi.vcd");
    $dumpvars;
    clk = 0;
    rst_n = 0;
    #10 rst_n = 1;

    #2000 $finish;
end
always #5 clk = !clk;
reg [5:0]i;
always@(posedge clk or negedge rst_n)
if(!rst_n)
begin
    A <= 32'd0;
    B <= 32'd0;
    i <= 6'd0;
    start_sig <= 1'b0;
end
else begin
    case (i)
        0:
            if(done_sig[0]==1'b1)
            begin
                start_sig <= 0;
                i <= i + 1'b1;
            end else begin
                A <= 32'b01000000001000000000000000000000;
                B <= 32'b01000000101000000000000000000000;
                start_sig <=1'b1;
            end 
        1:
            if(done_sig[0]==1'b1)
            begin
                start_sig <= 0;
                i <= i + 1'b1;
            end else begin
                A <= 32'b01000000010010010001011010000111;
                B <= 32'b01000000010010010001011010000111;
                start_sig <=1'b1;
            end 
        default:i <= 0;
    endcase
end
endmodule

float/multi.vcd
$date
	Fri Feb 28 22:39:39 2020
$end
$version
	Icarus Verilog
$end
$timescale
	1ps
$end
$scope module multi_tb $end
$var wire 32 ! result [31:0] $end
$var wire 4 " done_sig [3:0] $end
$var reg 32 # A [31:0] $end
$var reg 32 $ B [31:0] $end
$var reg 1 % clk $end
$var reg 6 & i [5:0] $end
$var reg 1 ' rst_n $end
$var reg 1 ( start_sig $end
$scope module U1 $end
$var wire 32 ) A [31:0] $end
$var wire 32 * B [31:0] $end
$var wire 1 % clk $end
$var wire 32 + result [31:0] $end
$var wire 1 ' rst_n $end
$var wire 1 ( start_sig $end
$var wire 4 , done_sig [3:0] $end
$var reg 5 - i [4:0] $end
$var reg 1 . isDone $end
$var reg 1 / isOver $end
$var reg 1 0 isUnder $end
$var reg 1 1 isZero $end
$var reg 33 2 rA [32:0] $end
$var reg 33 3 rB [32:0] $end
$var reg 10 4 rExp [9:0] $end
$var reg 48 5 rM [47:0] $end
$var reg 32 6 rResult [31:0] $end
$var reg 1 7 rSign $end
$upscope $end
$upscope $end
$enddefinitions $end
#0
$dumpvars
07
b0 6
b0 5
b0 4
b0 3
b0 2
01
00
0/
0.
bx -
b0 ,
b0 +
bx *
bx )
x(
0'
bx &
0%
bx $
bx #
b0 "
b0 !
$end
#5
0(
b0 &
b0 $
b0 *
b0 #
b0 )
1%
#10
0%
1'
#15
1(
b1000000101000000000000000000000 $
b1000000101000000000000000000000 *
b1000000001000000000000000000000 #
b1000000001000000000000000000000 )
1%
#20
0%
#25
b0 -
1%
#30
0%
#35
b1 -
b11001000000000000000000000000000000000000000000 5
b10000011 4
b10000001101000000000000000000000 3
b10000000101000000000000000000000 2
1%
#40
0%
#45
b10 -
b10000010 4
b110010000000000000000000000000000000000000000000 5
1%
#50
0%
#55
b11 -
b1000001010010000000000000000000 !
b1000001010010000000000000000000 +
b1000001010010000000000000000000 6
1%
#60
0%
#65
b100 -
b1 "
b1 ,
1.
1%
#70
0%
#75
b0 -
b0 "
b0 ,
0.
b1 &
0(
1%
#80
0%
#85
1(
b1000000010010010001011010000111 $
b1000000010010010001011010000111 *
b1000000010010010001011010000111 #
b1000000010010010001011010000111 )
1%
#90
0%
#95
b1 -
b100111011111010001100001111110010111101100110001 5
b10000000110010010001011010000111 3
b10000000110010010001011010000111 2
1%
#100
0%
#105
b10 -
1%
#110
0%
#115
b11 -
b1000001000111011111010001100001 !
b1000001000111011111010001100001 +
b1000001000111011111010001100001 6
1%
#120
0%
#125
b100 -
b1 "
b1 ,
1.
1%
#130
0%
#135
b0 -
b0 "
b0 ,
0.
b10 &
0(
1%
#140
0%
#145
b0 &
1%
#150
0%
#155
1(
b1000000101000000000000000000000 $
b1000000101000000000000000000000 *
b1000000001000000000000000000000 #
b1000000001000000000000000000000 )
1%
#160
0%
#165
b1 -
b11001000000000000000000000000000000000000000000 5
b10000011 4
b10000001101000000000000000000000 3
b10000000101000000000000000000000 2
1%
#170
0%
#175
b10 -
b10000010 4
b110010000000000000000000000000000000000000000000 5
1%
#180
0%
#185
b11 -
b1000001010010000000000000000000 !
b1000001010010000000000000000000 +
b1000001010010000000000000000000 6
1%
#190
0%
#195
b100 -
b1 "
b1 ,
1.
1%
#200
0%
#205
b1 &
0(
b0 -
b0 "
b0 ,
0.
1%
#210
0%
#215
1(
b1000000010010010001011010000111 $
b1000000010010010001011010000111 *
b1000000010010010001011010000111 #
b1000000010010010001011010000111 )
1%
#220
0%
#225
b1 -
b100111011111010001100001111110010111101100110001 5
b10000000110010010001011010000111 3
b10000000110010010001011010000111 2
1%
#230
0%
#235
b10 -
1%
#240
0%
#245
b11 -
b1000001000111011111010001100001 !
b1000001000111011111010001100001 +
b1000001000111011111010001100001 6
1%
#250
0%
#255
b100 -
b1 "
b1 ,
1.
1%
#260
0%
#265
b10 &
0(
b0 -
b0 "
b0 ,
0.
1%
#270
0%
#275
b0 &
1%
#280
0%
#285
1(
b1000000101000000000000000000000 $
b1000000101000000000000000000000 *
b1000000001000000000000000000000 #
b1000000001000000000000000000000 )
1%
#290
0%
#295
b1 -
b11001000000000000000000000000000000000000000000 5
b10000011 4
b10000001101000000000000000000000 3
b10000000101000000000000000000000 2
1%
#300
0%
#305
b10 -
b10000010 4
b110010000000000000000000000000000000000000000000 5
1%
#310
0%
#315
b11 -
b1000001010010000000000000000000 !
b1000001010010000000000000000000 +
b1000001010010000000000000000000 6
1%
#320
0%
#325
b100 -
b1 "
b1 ,
1.
1%
#330
0%
#335
b0 -
b0 "
b0 ,
0.
b1 &
0(
1%
#340
0%
#345
1(
b1000000010010010001011010000111 $
b1000000010010010001011010000111 *
b1000000010010010001011010000111 #
b1000000010010010001011010000111 )
1%
#350
0%
#355
b1 -
b100111011111010001100001111110010111101100110001 5
b10000000110010010001011010000111 3
b10000000110010010001011010000111 2
1%
#360
0%
#365
b10 -
1%
#370
0%
#375
b11 -
b1000001000111011111010001100001 !
b1000001000111011111010001100001 +
b1000001000111011111010001100001 6
1%
#380
0%
#385
b100 -
b1 "
b1 ,
1.
1%
#390
0%
#395
b0 -
b0 "
b0 ,
0.
b10 &
0(
1%
#400
0%
#405
b0 &
1%
#410
0%
#415
1(
b1000000101000000000000000000000 $
b1000000101000000000000000000000 *
b1000000001000000000000000000000 #
b1000000001000000000000000000000 )
1%
#420
0%
#425
b1 -
b11001000000000000000000000000000000000000000000 5
b10000011 4
b10000001101000000000000000000000 3
b10000000101000000000000000000000 2
1%
#430
0%
#435
b10 -
b10000010 4
b110010000000000000000000000000000000000000000000 5
1%
#440
0%
#445
b11 -
b1000001010010000000000000000000 !
b1000001010010000000000000000000 +
b1000001010010000000000000000000 6
1%
#450
0%
#455
b100 -
b1 "
b1 ,
1.
1%
#460
0%
#465
b1 &
0(
b0 -
b0 "
b0 ,
0.
1%
#470
0%
#475
1(
b1000000010010010001011010000111 $
b1000000010010010001011010000111 *
b1000000010010010001011010000111 #
b1000000010010010001011010000111 )
1%
#480
0%
#485
b1 -
b100111011111010001100001111110010111101100110001 5
b10000000110010010001011010000111 3
b10000000110010010001011010000111 2
1%
#490
0%
#495
b10 -
1%
#500
0%
#505
b11 -
b1000001000111011111010001100001 !
b1000001000111011111010001100001 +
b1000001000111011111010001100001 6
1%
#510
0%
#515
b100 -
b1 "
b1 ,
1.
1%
#520
0%
#525
b10 &
0(
b0 -
b0 "
b0 ,
0.
1%
#530
0%
#535
b0 &
1%
#540
0%
#545
1(
b1000000101000000000000000000000 $
b1000000101000000000000000000000 *
b1000000001000000000000000000000 #
b1000000001000000000000000000000 )
1%
#550
0%
#555
b1 -
b11001000000000000000000000000000000000000000000 5
b10000011 4
b10000001101000000000000000000000 3
b10000000101000000000000000000000 2
1%
#560
0%
#565
b10 -
b10000010 4
b110010000000000000000000000000000000000000000000 5
1%
#570
0%
#575
b11 -
b1000001010010000000000000000000 !
b1000001010010000000000000000000 +
b1000001010010000000000000000000 6
1%
#580
0%
#585
b100 -
b1 "
b1 ,
1.
1%
#590
0%
#595
b0 -
b0 "
b0 ,
0.
b1 &
0(
1%
#600
0%
#605
1(
b1000000010010010001011010000111 $
b1000000010010010001011010000111 *
b1000000010010010001011010000111 #
b1000000010010010001011010000111 )
1%
#610
0%
#615
b1 -
b100111011111010001100001111110010111101100110001 5
b10000000110010010001011010000111 3
b10000000110010010001011010000111 2
1%
#620
0%
#625
b10 -
1%
#630
0%
#635
b11 -
b1000001000111011111010001100001 !
b1000001000111011111010001100001 +
b1000001000111011111010001100001 6
1%
#640
0%
#645
b100 -
b1 "
b1 ,
1.
1%
#650
0%
#655
b0 -
b0 "
b0 ,
0.
b10 &
0(
1%
#660
0%
#665
b0 &
1%
#670
0%
#675
1(
b1000000101000000000000000000000 $
b1000000101000000000000000000000 *
b1000000001000000000000000000000 #
b1000000001000000000000000000000 )
1%
#680
0%
#685
b1 -
b11001000000000000000000000000000000000000000000 5
b10000011 4
b10000001101000000000000000000000 3
b10000000101000000000000000000000 2
1%
#690
0%
#695
b10 -
b10000010 4
b110010000000000000000000000000000000000000000000 5
1%
#700
0%
#705
b11 -
b1000001010010000000000000000000 !
b1000001010010000000000000000000 +
b1000001010010000000000000000000 6
1%
#710
0%
#715
b100 -
b1 "
b1 ,
1.
1%
#720
0%
#725
b1 &
0(
b0 -
b0 "
b0 ,
0.
1%
#730
0%
#735
1(
b1000000010010010001011010000111 $
b1000000010010010001011010000111 *
b1000000010010010001011010000111 #
b1000000010010010001011010000111 )
1%
#740
0%
#745
b1 -
b100111011111010001100001111110010111101100110001 5
b10000000110010010001011010000111 3
b10000000110010010001011010000111 2
1%
#750
0%
#755
b10 -
1%
#760
0%
#765
b11 -
b1000001000111011111010001100001 !
b1000001000111011111010001100001 +
b1000001000111011111010001100001 6
1%
#770
0%
#775
b100 -
b1 "
b1 ,
1.
1%
#780
0%
#785
b10 &
0(
b0 -
b0 "
b0 ,
0.
1%
#790
0%
#795
b0 &
1%
#800
0%
#805
1(
b1000000101000000000000000000000 $
b1000000101000000000000000000000 *
b1000000001000000000000000000000 #
b1000000001000000000000000000000 )
1%
#810
0%
#815
b1 -
b11001000000000000000000000000000000000000000000 5
b10000011 4
b10000001101000000000000000000000 3
b10000000101000000000000000000000 2
1%
#820
0%
#825
b10 -
b10000010 4
b110010000000000000000000000000000000000000000000 5
1%
#830
0%
#835
b11 -
b1000001010010000000000000000000 !
b1000001010010000000000000000000 +
b1000001010010000000000000000000 6
1%
#840
0%
#845
b100 -
b1 "
b1 ,
1.
1%
#850
0%
#855
b0 -
b0 "
b0 ,
0.
b1 &
0(
1%
#860
0%
#865
1(
b1000000010010010001011010000111 $
b1000000010010010001011010000111 *
b1000000010010010001011010000111 #
b1000000010010010001011010000111 )
1%
#870
0%
#875
b1 -
b100111011111010001100001111110010111101100110001 5
b10000000110010010001011010000111 3
b10000000110010010001011010000111 2
1%
#880
0%
#885
b10 -
1%
#890
0%
#895
b11 -
b1000001000111011111010001100001 !
b1000001000111011111010001100001 +
b1000001000111011111010001100001 6
1%
#900
0%
#905
b100 -
b1 "
b1 ,
1.
1%
#910
0%
#915
b0 -
b0 "
b0 ,
0.
b10 &
0(
1%
#920
0%
#925
b0 &
1%
#930
0%
#935
1(
b1000000101000000000000000000000 $
b1000000101000000000000000000000 *
b1000000001000000000000000000000 #
b1000000001000000000000000000000 )
1%
#940
0%
#945
b1 -
b11001000000000000000000000000000000000000000000 5
b10000011 4
b10000001101000000000000000000000 3
b10000000101000000000000000000000 2
1%
#950
0%
#955
b10 -
b10000010 4
b110010000000000000000000000000000000000000000000 5
1%
#960
0%
#965
b11 -
b1000001010010000000000000000000 !
b1000001010010000000000000000000 +
b1000001010010000000000000000000 6
1%
#970
0%
#975
b100 -
b1 "
b1 ,
1.
1%
#980
0%
#985
b1 &
0(
b0 -
b0 "
b0 ,
0.
1%
#990
0%
#995
1(
b1000000010010010001011010000111 $
b1000000010010010001011010000111 *
b1000000010010010001011010000111 #
b1000000010010010001011010000111 )
1%
#1000
0%
#1005
b1 -
b100111011111010001100001111110010111101100110001 5
b10000000110010010001011010000111 3
b10000000110010010001011010000111 2
1%
#1010
0%
#1015
b10 -
1%
#1020
0%
#1025
b11 -
b1000001000111011111010001100001 !
b1000001000111011111010001100001 +
b1000001000111011111010001100001 6
1%
#1030
0%
#1035
b100 -
b1 "
b1 ,
1.
1%
#1040
0%
#1045
b10 &
0(
b0 -
b0 "
b0 ,
0.
1%
#1050
0%
#1055
b0 &
1%
#1060
0%
#1065
1(
b1000000101000000000000000000000 $
b1000000101000000000000000000000 *
b1000000001000000000000000000000 #
b1000000001000000000000000000000 )
1%
#1070
0%
#1075
b1 -
b11001000000000000000000000000000000000000000000 5
b10000011 4
b10000001101000000000000000000000 3
b10000000101000000000000000000000 2
1%
#1080
0%
#1085
b10 -
b10000010 4
b110010000000000000000000000000000000000000000000 5
1%
#1090
0%
#1095
b11 -
b1000001010010000000000000000000 !
b1000001010010000000000000000000 +
b1000001010010000000000000000000 6
1%
#1100
0%
#1105
b100 -
b1 "
b1 ,
1.
1%
#1110
0%
#1115
b0 -
b0 "
b0 ,
0.
b1 &
0(
1%
#1120
0%
#1125
1(
b1000000010010010001011010000111 $
b1000000010010010001011010000111 *
b1000000010010010001011010000111 #
b1000000010010010001011010000111 )
1%
#1130
0%
#1135
b1 -
b100111011111010001100001111110010111101100110001 5
b10000000110010010001011010000111 3
b10000000110010010001011010000111 2
1%
#1140
0%
#1145
b10 -
1%
#1150
0%
#1155
b11 -
b1000001000111011111010001100001 !
b1000001000111011111010001100001 +
b1000001000111011111010001100001 6
1%
#1160
0%
#1165
b100 -
b1 "
b1 ,
1.
1%
#1170
0%
#1175
b0 -
b0 "
b0 ,
0.
b10 &
0(
1%
#1180
0%
#1185
b0 &
1%
#1190
0%
#1195
1(
b1000000101000000000000000000000 $
b1000000101000000000000000000000 *
b1000000001000000000000000000000 #
b1000000001000000000000000000000 )
1%
#1200
0%
#1205
b1 -
b11001000000000000000000000000000000000000000000 5
b10000011 4
b10000001101000000000000000000000 3
b10000000101000000000000000000000 2
1%
#1210
0%
#1215
b10 -
b10000010 4
b110010000000000000000000000000000000000000000000 5
1%
#1220
0%
#1225
b11 -
b1000001010010000000000000000000 !
b1000001010010000000000000000000 +
b1000001010010000000000000000000 6
1%
#1230
0%
#1235
b100 -
b1 "
b1 ,
1.
1%
#1240
0%
#1245
b1 &
0(
b0 -
b0 "
b0 ,
0.
1%
#1250
0%
#1255
1(
b1000000010010010001011010000111 $
b1000000010010010001011010000111 *
b1000000010010010001011010000111 #
b1000000010010010001011010000111 )
1%
#1260
0%
#1265
b1 -
b100111011111010001100001111110010111101100110001 5
b10000000110010010001011010000111 3
b10000000110010010001011010000111 2
1%
#1270
0%
#1275
b10 -
1%
#1280
0%
#1285
b11 -
b1000001000111011111010001100001 !
b1000001000111011111010001100001 +
b1000001000111011111010001100001 6
1%
#1290
0%
#1295
b100 -
b1 "
b1 ,
1.
1%
#1300
0%
#1305
b10 &
0(
b0 -
b0 "
b0 ,
0.
1%
#1310
0%
#1315
b0 &
1%
#1320
0%
#1325
1(
b1000000101000000000000000000000 $
b1000000101000000000000000000000 *
b1000000001000000000000000000000 #
b1000000001000000000000000000000 )
1%
#1330
0%
#1335
b1 -
b11001000000000000000000000000000000000000000000 5
b10000011 4
b10000001101000000000000000000000 3
b10000000101000000000000000000000 2
1%
#1340
0%
#1345
b10 -
b10000010 4
b110010000000000000000000000000000000000000000000 5
1%
#1350
0%
#1355
b11 -
b1000001010010000000000000000000 !
b1000001010010000000000000000000 +
b1000001010010000000000000000000 6
1%
#1360
0%
#1365
b100 -
b1 "
b1 ,
1.
1%
#1370
0%
#1375
b0 -
b0 "
b0 ,
0.
b1 &
0(
1%
#1380
0%
#1385
1(
b1000000010010010001011010000111 $
b1000000010010010001011010000111 *
b1000000010010010001011010000111 #
b1000000010010010001011010000111 )
1%
#1390
0%
#1395
b1 -
b100111011111010001100001111110010111101100110001 5
b10000000110010010001011010000111 3
b10000000110010010001011010000111 2
1%
#1400
0%
#1405
b10 -
1%
#1410
0%
#1415
b11 -
b1000001000111011111010001100001 !
b1000001000111011111010001100001 +
b1000001000111011111010001100001 6
1%
#1420
0%
#1425
b100 -
b1 "
b1 ,
1.
1%
#1430
0%
#1435
b0 -
b0 "
b0 ,
0.
b10 &
0(
1%
#1440
0%
#1445
b0 &
1%
#1450
0%
#1455
1(
b1000000101000000000000000000000 $
b1000000101000000000000000000000 *
b1000000001000000000000000000000 #
b1000000001000000000000000000000 )
1%
#1460
0%
#1465
b1 -
b11001000000000000000000000000000000000000000000 5
b10000011 4
b10000001101000000000000000000000 3
b10000000101000000000000000000000 2
1%
#1470
0%
#1475
b10 -
b10000010 4
b110010000000000000000000000000000000000000000000 5
1%
#1480
0%
#1485
b11 -
b1000001010010000000000000000000 !
b1000001010010000000000000000000 +
b1000001010010000000000000000000 6
1%
#1490
0%
#1495
b100 -
b1 "
b1 ,
1.
1%
#1500
0%
#1505
b1 &
0(
b0 -
b0 "
b0 ,
0.
1%
#1510
0%
#1515
1(
b1000000010010010001011010000111 $
b1000000010010010001011010000111 *
b1000000010010010001011010000111 #
b1000000010010010001011010000111 )
1%
#1520
0%
#1525
b1 -
b100111011111010001100001111110010111101100110001 5
b10000000110010010001011010000111 3
b10000000110010010001011010000111 2
1%
#1530
0%
#1535
b10 -
1%
#1540
0%
#1545
b11 -
b1000001000111011111010001100001 !
b1000001000111011111010001100001 +
b1000001000111011111010001100001 6
1%
#1550
0%
#1555
b100 -
b1 "
b1 ,
1.
1%
#1560
0%
#1565
b10 &
0(
b0 -
b0 "
b0 ,
0.
1%
#1570
0%
#1575
b0 &
1%
#1580
0%
#1585
1(
b1000000101000000000000000000000 $
b1000000101000000000000000000000 *
b1000000001000000000000000000000 #
b1000000001000000000000000000000 )
1%
#1590
0%
#1595
b1 -
b11001000000000000000000000000000000000000000000 5
b10000011 4
b10000001101000000000000000000000 3
b10000000101000000000000000000000 2
1%
#1600
0%
#1605
b10 -
b10000010 4
b110010000000000000000000000000000000000000000000 5
1%
#1610
0%
#1615
b11 -
b1000001010010000000000000000000 !
b1000001010010000000000000000000 +
b1000001010010000000000000000000 6
1%
#1620
0%
#1625
b100 -
b1 "
b1 ,
1.
1%
#1630
0%
#1635
b0 -
b0 "
b0 ,
0.
b1 &
0(
1%
#1640
0%
#1645
1(
b1000000010010010001011010000111 $
b1000000010010010001011010000111 *
b1000000010010010001011010000111 #
b1000000010010010001011010000111 )
1%
#1650
0%
#1655
b1 -
b100111011111010001100001111110010111101100110001 5
b10000000110010010001011010000111 3
b10000000110010010001011010000111 2
1%
#1660
0%
#1665
b10 -
1%
#1670
0%
#1675
b11 -
b1000001000111011111010001100001 !
b1000001000111011111010001100001 +
b1000001000111011111010001100001 6
1%
#1680
0%
#1685
b100 -
b1 "
b1 ,
1.
1%
#1690
0%
#1695
b0 -
b0 "
b0 ,
0.
b10 &
0(
1%
#1700
0%
#1705
b0 &
1%
#1710
0%
#1715
1(
b1000000101000000000000000000000 $
b1000000101000000000000000000000 *
b1000000001000000000000000000000 #
b1000000001000000000000000000000 )
1%
#1720
0%
#1725
b1 -
b11001000000000000000000000000000000000000000000 5
b10000011 4
b10000001101000000000000000000000 3
b10000000101000000000000000000000 2
1%
#1730
0%
#1735
b10 -
b10000010 4
b110010000000000000000000000000000000000000000000 5
1%
#1740
0%
#1745
b11 -
b1000001010010000000000000000000 !
b1000001010010000000000000000000 +
b1000001010010000000000000000000 6
1%
#1750
0%
#1755
b100 -
b1 "
b1 ,
1.
1%
#1760
0%
#1765
b1 &
0(
b0 -
b0 "
b0 ,
0.
1%
#1770
0%
#1775
1(
b1000000010010010001011010000111 $
b1000000010010010001011010000111 *
b1000000010010010001011010000111 #
b1000000010010010001011010000111 )
1%
#1780
0%
#1785
b1 -
b100111011111010001100001111110010111101100110001 5
b10000000110010010001011010000111 3
b10000000110010010001011010000111 2
1%
#1790
0%
#1795
b10 -
1%
#1800
0%
#1805
b11 -
b1000001000111011111010001100001 !
b1000001000111011111010001100001 +
b1000001000111011111010001100001 6
1%
#1810
0%
#1815
b100 -
b1 "
b1 ,
1.
1%
#1820
0%
#1825
b10 &
0(
b0 -
b0 "
b0 ,
0.
1%
#1830
0%
#1835
b0 &
1%
#1840
0%
#1845
1(
b1000000101000000000000000000000 $
b1000000101000000000000000000000 *
b1000000001000000000000000000000 #
b1000000001000000000000000000000 )
1%
#1850
0%
#1855
b1 -
b11001000000000000000000000000000000000000000000 5
b10000011 4
b10000001101000000000000000000000 3
b10000000101000000000000000000000 2
1%
#1860
0%
#1865
b10 -
b10000010 4
b110010000000000000000000000000000000000000000000 5
1%
#1870
0%
#1875
b11 -
b1000001010010000000000000000000 !
b1000001010010000000000000000000 +
b1000001010010000000000000000000 6
1%
#1880
0%
#1885
b100 -
b1 "
b1 ,
1.
1%
#1890
0%
#1895
b0 -
b0 "
b0 ,
0.
b1 &
0(
1%
#1900
0%
#1905
1(
b1000000010010010001011010000111 $
b1000000010010010001011010000111 *
b1000000010010010001011010000111 #
b1000000010010010001011010000111 )
1%
#1910
0%
#1915
b1 -
b100111011111010001100001111110010111101100110001 5
b10000000110010010001011010000111 3
b10000000110010010001011010000111 2
1%
#1920
0%
#1925
b10 -
1%
#1930
0%
#1935
b11 -
b1000001000111011111010001100001 !
b1000001000111011111010001100001 +
b1000001000111011111010001100001 6
1%
#1940
0%
#1945
b100 -
b1 "
b1 ,
1.
1%
#1950
0%
#1955
b0 -
b0 "
b0 ,
0.
b10 &
0(
1%
#1960
0%
#1965
b0 &
1%
#1970
0%
#1975
1(
b1000000101000000000000000000000 $
b1000000101000000000000000000000 *
b1000000001000000000000000000000 #
b1000000001000000000000000000000 )
1%
#1980
0%
#1985
b1 -
b11001000000000000000000000000000000000000000000 5
b10000011 4
b10000001101000000000000000000000 3
b10000000101000000000000000000000 2
1%
#1990
0%
#1995
b10 -
b10000010 4
b110010000000000000000000000000000000000000000000 5
1%
#2000
0%
#2005
b11 -
b1000001010010000000000000000000 !
b1000001010010000000000000000000 +
b1000001010010000000000000000000 6
1%
