roundRobinArbiter/arbiter.v
//----------------------------------------------------
// A four level, round-robin arbiter. This was
// orginally coded by WD Peterson in VHDL.
//----------------------------------------------------
module arbiter (
  clk,    
  rst,    
  req3,   
  req2,   
  req1,   
  req0,   
  gnt3,   
  gnt2,   
  gnt1,   
  gnt0   
);
// --------------Port Declaration----------------------- 
input           clk;    
input           rst;    
input           req3;   
input           req2;   
input           req1;   
input           req0;   
output          gnt3;   
output          gnt2;   
output          gnt1;   
output          gnt0;   

//--------------Internal Registers----------------------
wire    [1:0]   gnt       ;   
wire            comreq    ; 
wire            beg       ;
wire   [1:0]    lgnt      ;//当前granted的master标号
wire            lcomreq   ;
reg             lgnt0     ;//grant的one-hot编码值
reg             lgnt1     ;//grant的one-hot编码值
reg             lgnt2     ;//grant的one-hot编码值
reg             lgnt3     ;//grant的one-hot编码值
reg             lasmask   ;//
reg             lmask0    ;//
reg             lmask1    ;//
reg             ledge     ;

//--------------Code Starts Here----------------------- 
always @ (posedge clk)
if (rst) begin
  lgnt0 <= 0;
  lgnt1 <= 0;
  lgnt2 <= 0;
  lgnt3 <= 0;
end else begin                                     
  lgnt0 <=(~lcomreq & ~lmask1 & ~lmask0 & ~req3 & ~req2 & ~req1 & req0)//当前0号优先级最低
        | (~lcomreq & ~lmask1 &  lmask0 & ~req3 & ~req2 &  req0)//当前1号优先级最低；没有连续申请总线；2号3号没有发起申请；0号发起申请
        | (~lcomreq &  lmask1 & ~lmask0 & ~req3 &  req0)//当前2号优先级最低；没有连续申请总线；3号没有发起申请；0号发起申请
        | (~lcomreq &  lmask1 &  lmask0 & req0  )//lmask1和lmask0都为1：当前3号优先级最低；没有连续申请总线；0号发起申请
        | ( lcomreq & lgnt0 );//占总总线，且再次发起请求
  lgnt1 <=(~lcomreq & ~lmask1 & ~lmask0 &  req1)//当前1号优先级最低；没有连续申请总线；1号发起申请
        | (~lcomreq & ~lmask1 &  lmask0 & ~req3 & ~req2 &  req1 & ~req0)//当前2号优先级最低；没有连续申请总线；0，2，3没有发起申请；1号发起申请
        | (~lcomreq &  lmask1 & ~lmask0 & ~req3 &  req1 & ~req0)
        | (~lcomreq &  lmask1 &  lmask0 &  req1 & ~req0)
        | ( lcomreq &  lgnt1);
  lgnt2 <=(~lcomreq & ~lmask1 & ~lmask0 &  req2  & ~req1)
        | (~lcomreq & ~lmask1 &  lmask0 &  req2)
        | (~lcomreq &  lmask1 & ~lmask0 & ~req3 &  req2  & ~req1 & ~req0)
        | (~lcomreq &  lmask1 &  lmask0 &  req2 & ~req1 & ~req0)
        | ( lcomreq &  lgnt2);
  lgnt3 <=(~lcomreq & ~lmask1 & ~lmask0 & req3  & ~req2 & ~req1)
        | (~lcomreq & ~lmask1 &  lmask0 & req3  & ~req2)
        | (~lcomreq &  lmask1 & ~lmask0 & req3)
        | (~lcomreq &  lmask1 &  lmask0 & req3  & ~req2 & ~req1 & ~req0)
        | ( lcomreq & lgnt3);
end 

//----------------------------------------------------
// lasmask state machine.
//----------------------------------------------------
assign beg = (req3 | req2 | req1 | req0) & ~lcomreq;//下一个时钟总线可用，且发起了请求
always @ (posedge clk)
begin                                     
  lasmask <= (beg & ~ledge & ~lasmask);//从空闲或者重复请求中进入新的忙时，有一个高脉冲，这个高脉冲用于定义接下来的优先级
  ledge   <= (beg & ~ledge &  lasmask) 
          |  (beg &  ledge & ~lasmask);
end 

//----------------------------------------------------
// comreq logic.当前某个master占用总线时，同一个master再次发生请求，则输出为1，否则为0；若为1则下一时钟的总线已经被占用；若为0则下一时钟的总线可以分配
//----------------------------------------------------
assign lcomreq = ( req3 & lgnt3 )
                | ( req2 & lgnt2 )
                | ( req1 & lgnt1 )
                | ( req0 & lgnt0 );

//----------------------------------------------------
// Encoder logic.将one-hot编码为BCD
//----------------------------------------------------
assign  lgnt =  {(lgnt3 | lgnt2),(lgnt3 | lgnt1)};

//----------------------------------------------------
// lmask register.
//----------------------------------------------------
always @ (posedge clk )
if( rst ) begin
  lmask1 <= 0;
  lmask0 <= 0;
end else if(lasmask) begin//若从空闲进入忙状态，更新lmask，lmask为最低的优先级
  lmask1 <= lgnt[1];
  lmask0 <= lgnt[0];
end else begin
  lmask1 <= lmask1;
  lmask0 <= lmask0;
end 

assign comreq = lcomreq;
assign gnt    = lgnt;
//----------------------------------------------------
// Drive the outputs
//----------------------------------------------------
assign gnt3   = lgnt3;
assign gnt2   = lgnt2;
assign gnt1   = lgnt1;
assign gnt0   = lgnt0;

endmodule

roundRobinArbiter/arbiter_tb.v
`include "arbiter.v"
module top ();

reg             clk;    
reg             rst;    
reg             req3;   
reg             req2;   
reg             req1;   
reg             req0;   
wire            gnt3;   
wire            gnt2;   
wire            gnt1;   
wire            gnt0;  

// Clock generator
always #1 clk = ~clk;

initial begin
  $dumpfile ("arbiter.vcd");
  $dumpvars();
  clk = 0;
  rst = 1;
  req0 = 0;
  req1 = 0;
  req2 = 0;
  req3 = 0;
  #10 rst = 0;
  repeat (1) @ (posedge clk);
  req0 <= 1;
  repeat (1) @ (posedge clk);
  req0 <= 0;
  repeat (1) @ (posedge clk);
  req0 <= 1;
  req1 <= 1;
  repeat (1) @ (posedge clk);
  req0 <= 0;
  //req2 <= 1;
  req1 <= 0;
  repeat (1) @ (posedge clk);
  req3 <= 1;
  req2 <= 0;
  repeat (1) @ (posedge clk);
  req3 <= 0;
  repeat (1) @ (posedge clk);
  req0 <= 0;
  repeat (1) @ (posedge clk);

    repeat (1) @ (posedge clk);
  req0 <= 1;
  repeat (1) @ (posedge clk);
  req0 <= 0;
  repeat (1) @ (posedge clk);
  req0 <= 1;
  req1 <= 1;
  repeat (1) @ (posedge clk);
  req0 <= 0;
  req2 <= 1;
  req1 <= 0;
  repeat (1) @ (posedge clk);
  req3 <= 1;
  req2 <= 0;
  repeat (1) @ (posedge clk);
  req2 <= 1;
  repeat (1) @ (posedge clk);
  repeat (1) @ (posedge clk);
  req2 <= 0;
  repeat (1) @ (posedge clk);
  req0 <= 0;
  req3 <= 0;
  repeat (1) @ (posedge clk);
  req0 <= 1;
   req1 <= 1;
  repeat (1) @ (posedge clk);
  req0 <= 0;
  req1 <= 1;
  repeat (1) @ (posedge clk);
  req1 <= 0;
  req2 <= 1;
  repeat (1) @ (posedge clk);
  req2 <= 0;
  req3<= 1;
  repeat (1) @ (posedge clk);
  req3<= 0;
  req0 <= 1;
  req1 <= 1;
  repeat (1) @ (posedge clk);
  req0 <= 0;
  req1 <= 1;
  repeat (1) @ (posedge clk);
  req1 <= 0;
  req2 <= 1;
  repeat (1) @ (posedge clk);
  req2 <= 0;
  req3<= 1;
  repeat (1) @ (posedge clk);
  req3<= 0;
  #30 $finish;
end 

// Connect the DUT
arbiter U (
 clk,    
 rst,    
 req3,   
 req2,   
 req1,   
 req0,   
 gnt3,   
 gnt2,   
 gnt1,   
 gnt0   
);

endmodule

roundRobinArbiter/arbiter.vcd
$date
	Tue Feb 18 16:14:30 2020
$end
$version
	Icarus Verilog
$end
$timescale
	1s
$end
$scope module top $end
$var wire 1 ! gnt3 $end
$var wire 1 " gnt2 $end
$var wire 1 # gnt1 $end
$var wire 1 $ gnt0 $end
$var reg 1 % clk $end
$var reg 1 & req0 $end
$var reg 1 ' req1 $end
$var reg 1 ( req2 $end
$var reg 1 ) req3 $end
$var reg 1 * rst $end
$scope module U $end
$var wire 1 + beg $end
$var wire 1 % clk $end
$var wire 1 , comreq $end
$var wire 2 - gnt [1:0] $end
$var wire 1 $ gnt0 $end
$var wire 1 # gnt1 $end
$var wire 1 " gnt2 $end
$var wire 1 ! gnt3 $end
$var wire 1 . lcomreq $end
$var wire 1 & req0 $end
$var wire 1 ' req1 $end
$var wire 1 ( req2 $end
$var wire 1 ) req3 $end
$var wire 1 * rst $end
$var wire 2 / lgnt [1:0] $end
$var reg 1 0 lasmask $end
$var reg 1 1 ledge $end
$var reg 1 2 lgnt0 $end
$var reg 1 3 lgnt1 $end
$var reg 1 4 lgnt2 $end
$var reg 1 5 lgnt3 $end
$var reg 1 6 lmask0 $end
$var reg 1 7 lmask1 $end
$upscope $end
$upscope $end
$enddefinitions $end
#0
$dumpvars
x7
x6
x5
x4
x3
x2
x1
x0
bx /
0.
bx -
0,
0+
1*
0)
0(
0'
0&
0%
x$
x#
x"
x!
$end
#1
b0 -
b0 /
0!
05
0"
04
0#
03
0$
02
01
00
06
07
1%
#2
0%
#3
1%
#4
0%
#5
1%
#6
0%
#7
1%
#8
0%
#9
1%
#10
0%
0*
#11
1+
1&
1%
#12
0%
#13
0+
0&
1$
12
10
1%
#14
0%
#15
1+
00
0$
02
1'
1&
1%
#16
0%
#17
0+
b1 -
b1 /
0'
0&
1#
13
10
1%
#18
0%
#19
1+
b0 -
b0 /
16
00
0#
03
1)
1%
#20
0%
#21
0+
b11 -
b11 /
0)
1!
15
10
1%
#22
0%
#23
b0 -
b0 /
17
00
0!
05
1%
#24
0%
#25
1%
#26
0%
#27
1+
1&
1%
#28
0%
#29
0+
0&
1$
12
10
1%
#30
0%
#31
1+
06
07
00
0$
02
1'
1&
1%
#32
0%
#33
b1 -
b1 /
0'
1(
0&
1#
13
10
1%
#34
0%
#35
b10 -
b10 /
16
11
00
1"
14
0#
03
0(
1)
1%
#36
0%
#37
0+
1,
1.
b11 -
b11 /
1(
1!
15
0"
04
1%
#38
0%
#39
01
1%
#40
0%
#41
0(
1%
#42
0%
#43
0,
0.
0)
1%
#44
0%
#45
1+
b0 -
b0 /
1'
1&
0!
05
1%
#46
0%
#47
10
1$
12
0&
1%
#48
0%
#49
1+
b1 -
b1 /
1(
0'
1#
13
0$
02
11
00
06
1%
#50
0%
#51
b10 -
b10 /
1"
14
0#
03
1)
0(
1%
#52
0%
#53
b11 -
b11 /
1'
1&
0)
1!
15
0"
04
1%
#54
0%
#55
0+
1,
1.
b1 -
b1 /
0!
05
1#
13
0&
1%
#56
0%
#57
1+
0,
0.
1(
0'
01
1%
#58
0%
#59
b10 -
b10 /
10
1"
14
0#
03
1)
0(
1%
#60
0%
#61
0+
b11 -
b11 /
0)
1!
15
0"
04
11
00
17
1%
#62
0%
#63
b0 -
b0 /
01
0!
05
1%
