booth/boothu.v
module BOOTHU(
    clk,
    rst_n,
    Start_sig,
    A,
    B,
    Done_sig,
    Product
);
    parameter DATAWIDTH = 8;
    // paramter for state
    parameter   INIT = 4'b0001;
    parameter   OPER = 4'b0010;
    parameter   RSHIFT = 4'b0100;
    parameter   OUT = 4'b1000;
    parameter   OUT2 = 4'b1100;
    // input port------------------
    input   clk;
    input   rst_n;
    input   Start_sig;
    input   [DATAWIDTH-1:0]     A;//被乘数
    input   [DATAWIDTH-1:0]     B;//乘数
    // output ports------------------
    output  Done_sig;
    output  [2*DATAWIDTH-1:0]   Product;   
    // internal variables-------------
    reg     [DATAWIDTH-1:0]     A_n;
    reg     [2*DATAWIDTH:0]     booth_p;
    reg     [10:0]  counter;//counter for state count
    reg     [3:0]   state;
    reg     Done;
    reg     Start_sig_reg;
    // code starts here---------------
    always @(posedge clk, negedge rst_n) begin
        if(!rst_n)begin
            booth_p <= 0;
            Done <= 0;
            A_n <= 0;
            counter <= 0;
            state <= INIT;
        end
        else begin   
            if(Start_sig)//可以计算         
                case (state)
                INIT:begin
                    Done <= 1'b0;
                    A_n <= (~A+1'b1);
                    booth_p <= {{(DATAWIDTH-1){1'b0}},B,2'b00};
                    state <= OPER;
                    //counter <=  1'b1;
                end
                OPER:begin
                    //counter <= counter + 1'b1;
                    case(booth_p[2:1])
                        2'b01:begin
                            booth_p <= {{booth_p[2*DATAWIDTH],booth_p[2*DATAWIDTH:DATAWIDTH+2]}+A,booth_p[DATAWIDTH+1:1]};
                        end
                        2'b10:begin
                            booth_p <= {{booth_p[2*DATAWIDTH],booth_p[2*DATAWIDTH:DATAWIDTH+2]}+A_n,booth_p[DATAWIDTH+1:1]};
                        end
                        default: begin
                            booth_p <= {booth_p[2*DATAWIDTH],booth_p[2*DATAWIDTH:1]};;
                        end
                    endcase
                    //state <= RSHIFT;
                //end
                //RSHIFT:begin
                    counter <= counter + 1'b1;
                    
                //    booth_p <= {booth_p[2*DATAWIDTH],booth_p[2*DATAWIDTH:1]};
                    if(counter == DATAWIDTH-1)
                        state <= OUT;
                    else    state <= OPER;
                end
                OUT:begin
                    booth_p <= {booth_p[2*DATAWIDTH],booth_p[2*DATAWIDTH:1]};;
                    Done <= 1'b1;
                    state <= OUT2;
                    //counter <= counter + 1'b1;
                end
                OUT2:begin
                    Done <= 1'b0;
                    state <= INIT;
                end
                default: begin
                    booth_p <= 0;
                    Done <= 0;
                    A_n <= 0;
                    counter <= 0;
                    state <= INIT;
                end
            endcase
        end
    end

    // always @(posedge clk or negedge rst_n)
    // if(!rst_n)begin
    //     state <= INIT;
    //     Start_sig_reg <= 0;
    // end
    // else begin
    //     Start_sig_reg <= Start_sig;
    //     if(counter==0 && Start_sig_reg==1'b0 && Start_sig==1'b1) state <= OPER;//
    //     else if (counter == 2*DATAWIDTH)    state <= OUT;
    //     else if(counter[0] == 1'b0) state <= OPER;
    //     else if(counter[0] == 1'b1 && counter != 1) state <= RSHIFT; 
    //     else state<= INIT;
    // end

    assign Done_sig = Done;
    assign Product = booth_p[2*DATAWIDTH:1];
endmodule

booth/booth_tb.v
`include "boothu.v"
module booth_tb;

    reg clk;
    reg rst_n;
    reg Start_sig;
    reg [7:0]Avalue;
    reg [7:0]Bvalue;
    wire Done_sig;
    wire [15:0]Product;

BOOTHU #(8)booth_u1(
    .clk(clk),
    .rst_n(rst_n),
    .Start_sig(Start_sig),
    .A(Avalue),
    .B(Bvalue),
    .Done_sig(Done_sig),
    .Product(Product)
);

initial begin
    $dumpfile("booth.vcd");
    $dumpvars;
    clk = 0;
    rst_n = 0;
    Start_sig = 0;
    Avalue = 8'b00010000;
    Bvalue = 8'b00000100;
    #CLOCKPERIOD rst_n = 1;
    #CLOCKPERIOD Start_sig = 1;

    
    #400 $finish;
end
parameter CLOCKPERIOD = 10;
always #(CLOCKPERIOD/2) clk = !clk;
always @(posedge clk)
if(Done_sig == 1)
    Start_sig <=0;
endmodule

booth/booth.vcd
$date
	Wed Feb 19 21:49:28 2020
$end
$version
	Icarus Verilog
$end
$timescale
	1s
$end
$scope module booth_tb $end
$var wire 16 ! Product [15:0] $end
$var wire 1 " Done_sig $end
$var reg 8 # Avalue [7:0] $end
$var reg 8 $ Bvalue [7:0] $end
$var reg 1 % Start_sig $end
$var reg 1 & clk $end
$var reg 1 ' rst_n $end
$scope module booth_u1 $end
$var wire 8 ( A [7:0] $end
$var wire 8 ) B [7:0] $end
$var wire 1 " Done_sig $end
$var wire 1 % Start_sig $end
$var wire 1 & clk $end
$var wire 1 ' rst_n $end
$var wire 16 * Product [15:0] $end
$var reg 8 + A_n [7:0] $end
$var reg 1 , Done $end
$var reg 17 - booth_p [16:0] $end
$var reg 11 . counter [10:0] $end
$var reg 4 / state [3:0] $end
$upscope $end
$upscope $end
$enddefinitions $end
#0
$dumpvars
b1 /
b0 .
b0 -
0,
b0 +
b0 *
b100 )
b10000 (
0'
0&
0%
b100 $
b10000 #
0"
b0 !
$end
#5
1&
#10
0&
1'
#15
1&
#20
0&
1%
#25
b1000 !
b1000 *
b10 /
b10000 -
b11110000 +
1&
#30
0&
#35
b100 !
b100 *
b1 .
b1000 -
1&
#40
0&
#45
b10 !
b10 *
b10 .
b100 -
1&
#50
0&
#55
b1111000000000001 !
b1111000000000001 *
b11 .
b11110000000000010 -
1&
#60
0&
#65
b100000000000 !
b100000000000 *
b100 .
b1000000000001 -
1&
#70
0&
#75
b10000000000 !
b10000000000 *
b101 .
b100000000000 -
1&
#80
0&
#85
b1000000000 !
b1000000000 *
b110 .
b10000000000 -
1&
#90
0&
#95
b100000000 !
b100000000 *
b111 .
b1000000000 -
1&
#100
0&
#105
b10000000 !
b10000000 *
b1000 /
b1000 .
b100000000 -
1&
#110
0&
#115
b1000000 !
b1000000 *
b1100 /
1"
1,
b10000000 -
1&
#120
0&
#125
b1 /
0"
0,
0%
1&
